setup.py
refplay/__init__.py
refplay/refplay.py
refplay.egg-info/PKG-INFO
refplay.egg-info/SOURCES.txt
refplay.egg-info/dependency_links.txt
refplay.egg-info/not-zip-safe
refplay.egg-info/top_level.txt