Metadata-Version: 1.1
Name: refplay
Version: 0.0.1
Summary: Reflex demo header parser
Home-page: http://github.com/b1naryth1ef/refplay
Author: Andrei
Author-email: andrei.zbikowski@gmail.com
License: Apache 2.0
Platform: UNKNOWN
Classifier: Development Status :: 3 - Alpha
Classifier: Intended Audience :: Developers
Classifier: Natural Language :: English
Classifier: License :: OSI Approved :: Apache Software License
Classifier: Programming Language :: Python
Classifier: Programming Language :: Python :: 2.6
Classifier: Programming Language :: Python :: 2.7
Classifier: Programming Language :: Python :: 3.2
Classifier: Programming Language :: Python :: 3.3
